ebdamame/__init__.py
ebdamame/_docx_utils.py
ebdamame/docxtableconverter.py
ebdamame/exceptions.py
ebdamame/models.py
ebdamame/py.typed
ebdamame/version.py
ebdamame-1.0.0.dist-info/METADATA
ebdamame-1.0.0.dist-info/WHEEL
ebdamame-1.0.0.dist-info/licenses/LICENSE
ebdamame-1.0.0.dist-info/RECORD
