Metadata-Version: 2.4
Name: ebdamame
Version: 1.0.0
Summary: A scraper to library to scrape .docx files with 'Entscheidungsbaumdiagramm' tables into a truely machine readable structure
Project-URL: Changelog, https://github.com/Hochfrequenz/ebdamame/releases
Project-URL: Homepage, https://github.com/Hochfrequenz/ebdamame
Author-email: Hochfrequenz Unternehmensberatung GmbH <info@hochfrequenz.de>
License: GPL
License-File: LICENSE
Keywords: EBD,Energiewirtschaft,Marktkommunikation
Classifier: Development Status :: 5 - Production/Stable
Classifier: Environment :: Console
Classifier: Intended Audience :: Developers
Classifier: License :: OSI Approved :: GNU General Public License v3 (GPLv3)
Classifier: Operating System :: OS Independent
Classifier: Programming Language :: Python
Classifier: Programming Language :: Python :: 3 :: Only
Classifier: Programming Language :: Python :: 3.11
Classifier: Programming Language :: Python :: 3.12
Classifier: Programming Language :: Python :: 3.13
Classifier: Programming Language :: Python :: 3.14
Requires-Python: >=3.11
Requires-Dist: click>=8.1.8
Requires-Dist: more-itertools>=10.5.0
Requires-Dist: pydantic>=2.0
Requires-Dist: python-docx>=1.1.2
Requires-Dist: rebdhuhn>=0.22.0
Provides-Extra: coverage
Requires-Dist: coverage==7.13.0; extra == 'coverage'
Provides-Extra: formatting
Requires-Dist: black==25.12.0; extra == 'formatting'
Requires-Dist: isort==7.0.0; extra == 'formatting'
Provides-Extra: linting
Requires-Dist: pylint==4.0.4; extra == 'linting'
Provides-Extra: spellcheck
Requires-Dist: codespell==2.4.1; extra == 'spellcheck'
Provides-Extra: test-packaging
Requires-Dist: build==1.3.0; extra == 'test-packaging'
Requires-Dist: twine==6.2.0; extra == 'test-packaging'
Provides-Extra: tests
Requires-Dist: pytest-subtests==0.15.0; extra == 'tests'
Requires-Dist: pytest==9.0.2; extra == 'tests'
Requires-Dist: syrupy==5.0.0; extra == 'tests'
Provides-Extra: type-check
Requires-Dist: mypy==1.19.1; extra == 'type-check'
